rivers/__init__.py
rivers-0.1.0.dist-info/METADATA
rivers-0.1.0.dist-info/WHEEL
rivers-0.1.0.dist-info/top_level.txt
rivers-0.1.0.dist-info/RECORD
