Metadata-Version: 2.4
Name: rivers
Version: 0.1.0
Summary: Orchestration backed by Rust - Flowing through the rive-rs
Requires-Python: >=3.9
